sirfshampoo/__init__.py
sirfshampoo/combiner.py
sirfshampoo/optimizer.py
sirfshampoo/utils.py
sirfshampoo-0.0.1.dist-info/LICENSE
sirfshampoo-0.0.1.dist-info/METADATA
sirfshampoo-0.0.1.dist-info/WHEEL
sirfshampoo-0.0.1.dist-info/top_level.txt
sirfshampoo-0.0.1.dist-info/RECORD
