Metadata-Version: 2.1
Name: sirfshampoo
Version: 0.0.1
Summary: Structured inverse- and root-free Shampoo
Home-page: https://github.com/f-dangel/sirfshampoo
Author: Felix Dangel
Author-email: 
License: MIT
Keywords: python package,template,literate config
Platform: any
Classifier: Development Status :: 3 - Alpha
Classifier: License :: OSI Approved :: MIT License
Classifier: Operating System :: OS Independent
Classifier: Programming Language :: Python :: 3.9
Classifier: Programming Language :: Python :: 3.10
Classifier: Programming Language :: Python :: 3.11
Requires-Python: >=3.9
License-File: LICENSE
Requires-Dist: singd >=0.0.3
Requires-Dist: torch
Requires-Dist: numpy
Provides-Extra: doc
Requires-Dist: mkdocs ==1.4.3 ; extra == 'doc'
Requires-Dist: mkdocs-material ==9.1.17 ; extra == 'doc'
Requires-Dist: mkdocstrings[python] ==0.22.0 ; extra == 'doc'
Requires-Dist: mkdocs-gallery ==0.7.8 ; extra == 'doc'
Requires-Dist: torchvision ; extra == 'doc'
Provides-Extra: lint
Requires-Dist: black ; extra == 'lint'
Requires-Dist: isort ; extra == 'lint'
Requires-Dist: flake8 ; extra == 'lint'
Requires-Dist: mccabe ; extra == 'lint'
Requires-Dist: pycodestyle ; extra == 'lint'
Requires-Dist: pyflakes ; extra == 'lint'
Requires-Dist: pep8-naming ; extra == 'lint'
Requires-Dist: flake8-bugbear ; extra == 'lint'
Requires-Dist: flake8-comprehensions ; extra == 'lint'
Requires-Dist: flake8-tidy-imports ; extra == 'lint'
Requires-Dist: darglint ; extra == 'lint'
Requires-Dist: pydocstyle ; extra == 'lint'
Provides-Extra: test
Requires-Dist: coveralls ; extra == 'test'
Requires-Dist: pytest ; extra == 'test'
Requires-Dist: pytest-cov ; extra == 'test'
Requires-Dist: pytest-optional-tests ; extra == 'test'
Requires-Dist: torchvision ; extra == 'test'
